MED3pa/__init__.py
MED3pa/datasets/__init__.py
MED3pa/datasets/loading_context.py
MED3pa/datasets/loading_strategies.py
MED3pa/datasets/manager.py
MED3pa/datasets/masked.py
MED3pa/med3pa/__init__.py
MED3pa/med3pa/experiment.py
MED3pa/med3pa/mdr.py
MED3pa/med3pa/models.py
MED3pa/med3pa/profiles.py
MED3pa/med3pa/results.py
MED3pa/med3pa/tree.py
MED3pa/med3pa/uncertainty.py
MED3pa/models/__init__.py
MED3pa/models/abstract_metrics.py
MED3pa/models/abstract_models.py
MED3pa/models/base.py
MED3pa/models/classification_metrics.py
MED3pa/models/concrete_classifiers.py
MED3pa/models/concrete_regressors.py
MED3pa/models/data_strategies.py
MED3pa/models/dtr_params.py
MED3pa/models/factories.py
MED3pa/models/regression_metrics.py
MED3pa/models/rfr_params.py
MED3pa/models/xgboost_params.py
MED3pa/visualization/__init__.py
MED3pa/visualization/mdr_visualization.py
MED3pa/visualization/profiles_visualization.py
MED3pa/visualization/tree_template/__init__.py
MED3pa/visualization/tree_template/script.js
MED3pa/visualization/tree_template/style.css
MED3pa/visualization/tree_template/tree.html
MED3pa/visualizer/__init__.py
MED3pa/visualizer/tree_visualizer.py
MED3pa/visualizer/tree_template/script.js
MED3pa/visualizer/tree_template/style.css
MED3pa/visualizer/tree_template/tree.html
med3pa-1.0.1.dist-info/licenses/LICENSE
med3pa-1.0.1.dist-info/METADATA
med3pa-1.0.1.dist-info/WHEEL
med3pa-1.0.1.dist-info/top_level.txt
med3pa-1.0.1.dist-info/RECORD
