Metadata-Version: 2.4
Name: MED3pa
Version: 1.0.1
Summary: Python Open-source package for ensuring robust and reliable ML models deployments
Home-page: https://github.com/MEDomicsLab/MED3pa
Author: MEDomics consortium
Author-email: medomics.info@gmail.com
Project-URL: Documentation, https://med3pa.readthedocs.io/en/latest/
Project-URL: Github, https://github.com/MEDomicsLab/MED3pa
Requires-Python: >=3.9
License-File: LICENSE
Requires-Dist: checkpointer==2.1.0
Requires-Dist: numpy<2.1.0,>=1.21.0
Requires-Dist: pandas<3.0.0,>=1.4.0
Requires-Dist: PyYAML<7.0,>=5.4
Requires-Dist: matplotlib==3.9.2
Requires-Dist: ray>=2.37.0
Requires-Dist: relib==1.2.0
Requires-Dist: scikit_learn<2.0,>=1.0
Requires-Dist: scipy<2.0,>=1.7
Requires-Dist: setuptools<70.0,>=49.6.0
Requires-Dist: torch<3.0,>=1.9.0
Requires-Dist: tqdm<5.0,>=4.50.0
Requires-Dist: xgboost==2.1.1
Dynamic: author
Dynamic: author-email
Dynamic: description
Dynamic: description-content-type
Dynamic: home-page
Dynamic: license-file
Dynamic: project-url
Dynamic: requires-dist
Dynamic: requires-python
Dynamic: summary
